README.rst
setup.py
solid/__init__.py
solid/exception.py
solid/transition.py
solid/util.py
solid.egg-info/PKG-INFO
solid.egg-info/SOURCES.txt
solid.egg-info/dependency_links.txt
solid.egg-info/top_level.txt
solid/machines/__init__.py
solid/machines/base_machine.py
solid/machines/stepped_machine.py
solid/states/__init__.py
solid/states/base_state.py
solid/states/boomerang_state.py
solid/states/decorators.py
solid/states/guarded_state.py
solid/states/single_target_state.py