Metadata-Version: 1.0
Name: solid
Version: 0.2.0
Summary: Pythonic state machines
Home-page: http://github.com/haaksmash/solid
Author: Haak Saxberg
Author-email: haak.erling@gmail.com
License: UNKNOWN
Platform: UNKNOWN
